{
  "tags": [],
  "chapters": [],
  "title": "Wastelands 2 - More Stories of the Apocalypse",
  "subtitle": "Famine, Death, War, and Pestilence - the Four Horsemen of the Apocalypse, the harbingers of Armageddon - these are our guides through the Wastelands....",
  "authors": [
    "John Joseph Adams"
  ],
  "narrators": [],
  "series": [],
  "genres": [
    "Fiction"
  ],
  "publishedYear": "1973",
  "publishedDate": null,
  "publisher": "Titan Books",
  "description": "Wastelands 2 - More Stories of the Apocalypse is a new anthology of post-apocalyptic literature from some of the most renowned science fiction and fantasy authors in the field today including George R.R. Martin, Hugh Howey, Junot Diaz, David Brin and many more. It is an eclectic mix of tales that explores famine, death, war, pestilence, and harbingers of the biblical apocalypse.",
  "isbn": "9781783291526",
  "asin": null,
  "language": null,
  "explicit": false,
  "abridged": false
}