{
  "tags": [],
  "chapters": [
    {
      "id": 0,
      "start": 0,
      "end": 36.616,
      "title": "Intro - Opening Credits ☕"
    },
    {
      "id": 1,
      "start": 36.616,
      "end": 42,
      "title": "Chapter Two: Project Alicization, July 2026"
    },
    {
      "id": 2,
      "start": 42,
      "end": 3179.251,
      "title": "~ Chapter 1"
    },
    {
      "id": 3,
      "start": 3179.251,
      "end": 9539.637,
      "title": "~ Chapter 2"
    },
    {
      "id": 4,
      "start": 9539.637,
      "end": 11078.191,
      "title": "~ Chapter 3"
    },
    {
      "id": 5,
      "start": 11078.191,
      "end": 11084,
      "title": "Chapter Three: Zakkaria Tournament, August 378 HE"
    },
    {
      "id": 6,
      "start": 11084,
      "end": 11516.514,
      "title": "~ Chapter 1"
    },
    {
      "id": 7,
      "start": 11516.514,
      "end": 12933.697,
      "title": "~ Chapter 2"
    },
    {
      "id": 8,
      "start": 12933.697,
      "end": 14254.03,
      "title": "~ Chapter 3"
    },
    {
      "id": 9,
      "start": 14254.03,
      "end": 15910.634,
      "title": "~ Chapter 4"
    },
    {
      "id": 10,
      "start": 15910.634,
      "end": 15919,
      "title": "Chapter Four: Imperial Swordcraft Academy, March 380 HE"
    },
    {
      "id": 11,
      "start": 15919,
      "end": 18286.848,
      "title": "~ Chapter 1"
    },
    {
      "id": 12,
      "start": 18286.848,
      "end": 21131.338,
      "title": "~ Chapter 2"
    },
    {
      "id": 13,
      "start": 21131.338,
      "end": 22566.516,
      "title": "~ Chapter 3"
    },
    {
      "id": 14,
      "start": 22566.516,
      "end": 24195.419,
      "title": "~ Chapter 4"
    },
    {
      "id": 15,
      "start": 24195.419,
      "end": 26214.254,
      "title": "~ Chapter 5"
    },
    {
      "id": 16,
      "start": 26214.254,
      "end": 27412.542,
      "title": "~ Chapter 6"
    },
    {
      "id": 17,
      "start": 27412.542,
      "end": 27926.26,
      "title": "Interlude II"
    },
    {
      "id": 18,
      "start": 27926.26,
      "end": 28097,
      "title": "Outro - Ending Credits ☕"
    }
  ],
  "title": "Sword Art Online, Vol. 10: Alicization Running",
  "subtitle": null,
  "authors": [
    "Bryce Papenbrook",
    "Cherami Leigh"
  ],
  "narrators": [
    "Reki Kawahara"
  ],
  "series": [
    "Sword Art Online #10"
  ],
  "genres": [
    "Audiobook"
  ],
  "publishedYear": "July 10, 2012 (08-15-23)",
  "publishedDate": null,
  "publisher": "Yen Audio",
  "description": "Phantom",
  "isbn": null,
  "asin": null,
  "language": null,
  "explicit": false,
  "abridged": false
}