{
  "tags": [],
  "chapters": [
    {
      "id": 0,
      "start": 0,
      "end": 14,
      "title": "Intro - Opening Credits ☕"
    },
    {
      "id": 1,
      "start": 14,
      "end": 2157,
      "title": "Prologue: Class Up"
    },
    {
      "id": 2,
      "start": 2157,
      "end": 4877,
      "title": "Chapter One: The Heroes’ Teammates"
    },
    {
      "id": 3,
      "start": 4877,
      "end": 8210,
      "title": "Chapter Two: Meeting of the Heroes"
    },
    {
      "id": 4,
      "start": 8210,
      "end": 9527,
      "title": "Chapter Three: Power Up"
    },
    {
      "id": 5,
      "start": 9527,
      "end": 10213,
      "title": "Chapter Four: Weapon Copy"
    },
    {
      "id": 6,
      "start": 10213,
      "end": 11773,
      "title": "Chapter Five: Gravestones"
    },
    {
      "id": 7,
      "start": 11773,
      "end": 15117,
      "title": "Chapter Six: Cal Mira"
    },
    {
      "id": 8,
      "start": 15117,
      "end": 16127,
      "title": "Chapter Seven: The Tavern"
    },
    {
      "id": 9,
      "start": 16127,
      "end": 19928,
      "title": "Chapter Eight: Karma"
    },
    {
      "id": 10,
      "start": 19928,
      "end": 20545,
      "title": "Chapter Nine: Island Days"
    },
    {
      "id": 11,
      "start": 20545,
      "end": 23079,
      "title": "Chapter Ten: The Water Temple"
    },
    {
      "id": 12,
      "start": 23079,
      "end": 24710,
      "title": "Chapter Eleven: Inter-dimensional Whale"
    },
    {
      "id": 13,
      "start": 24710,
      "end": 27098,
      "title": "Chapter Twelve: L’Arc Berg"
    },
    {
      "id": 14,
      "start": 27098,
      "end": 29108,
      "title": "Chapter Thirteen: Soul-Healing Water"
    },
    {
      "id": 15,
      "start": 29108,
      "end": 29964,
      "title": "Epilogue: The Problem We Face"
    },
    {
      "id": 16,
      "start": 29964,
      "end": 31565,
      "title": "Extra Chapter: The Cal Mira Hot Springs"
    },
    {
      "id": 17,
      "start": 31565,
      "end": 31620,
      "title": "Outro - Ending Credits ☕"
    }
  ],
  "title": "The Rising of the Shield Hero, Vol. 05",
  "subtitle": null,
  "authors": [
    "Matthew Bridges"
  ],
  "narrators": [
    "Aneko Yusagi"
  ],
  "series": [
    "The Rising of the Shield Hero #05"
  ],
  "genres": [
    "Audiobook"
  ],
  "publishedYear": "April 24, 2014",
  "publishedDate": null,
  "publisher": "One Peace Books",
  "description": "Phantom",
  "isbn": null,
  "asin": null,
  "language": null,
  "explicit": false,
  "abridged": false
}